hello_robot_stretch_factory-0.5.7.data/scripts/RE1_migrate_contacts.py
hello_robot_stretch_factory-0.5.7.data/scripts/RE1_migrate_params.py
hello_robot_stretch_factory-0.5.7.data/scripts/REx_D435i_check.py
hello_robot_stretch_factory-0.5.7.data/scripts/REx_amend_venv_execs.py
hello_robot_stretch_factory-0.5.7.data/scripts/REx_base_calibrate_imu_collect.py
hello_robot_stretch_factory-0.5.7.data/scripts/REx_base_calibrate_imu_process.py
hello_robot_stretch_factory-0.5.7.data/scripts/REx_base_calibrate_wheel_separation.py
hello_robot_stretch_factory-0.5.7.data/scripts/REx_calibrate_gravity_comp.py
hello_robot_stretch_factory-0.5.7.data/scripts/REx_calibrate_guarded_contact.py
hello_robot_stretch_factory-0.5.7.data/scripts/REx_calibrate_range.py
hello_robot_stretch_factory-0.5.7.data/scripts/REx_camera_set_symlink.py
hello_robot_stretch_factory-0.5.7.data/scripts/REx_cliff_sensor_calibrate.py
hello_robot_stretch_factory-0.5.7.data/scripts/REx_comm_rates.py
hello_robot_stretch_factory-0.5.7.data/scripts/REx_discover_hello_devices.py
hello_robot_stretch_factory-0.5.7.data/scripts/REx_dmesg_monitor.py
hello_robot_stretch_factory-0.5.7.data/scripts/REx_dynamixel_id_change.py
hello_robot_stretch_factory-0.5.7.data/scripts/REx_dynamixel_id_scan.py
hello_robot_stretch_factory-0.5.7.data/scripts/REx_dynamixel_jog.py
hello_robot_stretch_factory-0.5.7.data/scripts/REx_dynamixel_reboot.py
hello_robot_stretch_factory-0.5.7.data/scripts/REx_dynamixel_set_baud.py
hello_robot_stretch_factory-0.5.7.data/scripts/REx_firmware_flash.py
hello_robot_stretch_factory-0.5.7.data/scripts/REx_firmware_updater.py
hello_robot_stretch_factory-0.5.7.data/scripts/REx_gamepad_configure.py
hello_robot_stretch_factory-0.5.7.data/scripts/REx_gripper_calibrate.py
hello_robot_stretch_factory-0.5.7.data/scripts/REx_hello_dynamixel_jog.py
hello_robot_stretch_factory-0.5.7.data/scripts/REx_stepper_calibration_YAML_to_flash.py
hello_robot_stretch_factory-0.5.7.dist-info/LICENSE.md
hello_robot_stretch_factory-0.5.7.dist-info/METADATA
hello_robot_stretch_factory-0.5.7.dist-info/WHEEL
hello_robot_stretch_factory-0.5.7.dist-info/top_level.txt
hello_robot_stretch_factory-0.5.7.dist-info/RECORD
