Metadata-Version: 2.1
Name: hello-robot-stretch-factory
Version: 0.5.7
Summary: Stretch Factory Tools
Home-page: https://github.com/hello-robot/stretch_factory
Author: Hello Robot Inc.
Author-email: support@hello-robot.com
Classifier: Programming Language :: Python :: 3
Classifier: Operating System :: OS Independent
Classifier: License :: OSI Approved :: GNU General Public License v3 (GPLv3)
License-File: LICENSE.md
Requires-Dist: future
Requires-Dist: pyserial
Requires-Dist: pyusb
Requires-Dist: gitpython
Requires-Dist: hello-robot-stretch-body (>=0.4.26)
Requires-Dist: tabulate
Requires-Dist: python-xlib
